setup.cfg
setup.py
pypcalc/__init__.py
pypcalc/__main__.py
pypcalc.egg-info/PKG-INFO
pypcalc.egg-info/SOURCES.txt
pypcalc.egg-info/dependency_links.txt
pypcalc.egg-info/entry_points.txt
pypcalc.egg-info/top_level.txt