Metadata-Version: 1.1
Name: pypcalc
Version: 0.2
Summary: Simple command-line tool for analyzing network addresses
Home-page: https://github.com/easypost/pypcalc
Author: EasyPost OSS
Author-email: oss@easypost.com
License: ISC
Keywords: networking
Platform: UNKNOWN
Classifier: Development Status :: 3 - Alpha
Classifier: Environment :: Console
Classifier: Programming Language :: Python
Classifier: Programming Language :: Python :: 2.7
Classifier: Programming Language :: Python :: 3.2
Classifier: Programming Language :: Python :: 3.3
Classifier: Programming Language :: Python :: 3.4
Classifier: Programming Language :: Python :: 3.5
Classifier: Intended Audience :: End Users/Desktop
Classifier: Operating System :: OS Independent
Classifier: License :: OSI Approved :: ISC License (ISCL)
Classifier: Topic :: System :: Networking
